KDVoucherUtil/VoucherUtil.py
KDVoucherUtil/WebserviceUtil.py
KDVoucherUtil/Worker.py
KDVoucherUtil/__init__.py
KDVoucherUtil-0.2.0.dist-info/METADATA
KDVoucherUtil-0.2.0.dist-info/WHEEL
KDVoucherUtil-0.2.0.dist-info/top_level.txt
KDVoucherUtil-0.2.0.dist-info/RECORD
