Metadata-Version: 2.1
Name: KDVoucherUtil
Version: 0.2.0
Summary: 金蝶云平台凭证批量处理封装工具。
Author: Arthur Yu
Author-email: arthurzero@homtail.com
License: MIT
Classifier: Development Status :: 1 - Planning
Classifier: Intended Audience :: Developers
Classifier: Programming Language :: Python :: 3
Classifier: Operating System :: Unix
Classifier: Operating System :: MacOS :: MacOS X
Classifier: Operating System :: Microsoft :: Windows
Requires-Dist: suds-jurko >=0.6
